RealtimeStock/__init__.py
RealtimeStock-1.0.2.dist-info/LICENSE
RealtimeStock-1.0.2.dist-info/METADATA
RealtimeStock-1.0.2.dist-info/WHEEL
RealtimeStock-1.0.2.dist-info/top_level.txt
RealtimeStock-1.0.2.dist-info/RECORD
