Metadata-Version: 2.1
Name: RealtimeStock
Version: 1.0.2
Summary: Realtime stock quote for Python
Home-page: https://github.com/Iceloof/RealtimeStock
Author: Hurin Hu
Author-email: hurin@live.ca
License: UNKNOWN
Platform: UNKNOWN
Classifier: Programming Language :: Python :: 3.8
Classifier: License :: OSI Approved :: MIT License
Classifier: Operating System :: OS Independent
Requires-Dist: requests
Requires-Dist: pytz
